douroucoulis/__init__.py
douroucoulis/douroucoulis_v0_1.py
douroucoulis-0.1.3.dist-info/METADATA
douroucoulis-0.1.3.dist-info/WHEEL
douroucoulis-0.1.3.dist-info/top_level.txt
douroucoulis-0.1.3.dist-info/RECORD
