Metadata-Version: 2.1
Name: douroucoulis
Version: 0.1.3
Summary: INformation-Theoretic model selection, multimodel inference, Machine Learning algorithms.
Home-page: https://github.com/douroucoulis-fr/douroucoulisdotpie
Author: Juan Pablo Perea-Rodriguez, Ph.D.
Author-email: douroucoulis-fr@gmail.com
Classifier: Programming Language :: Python :: 3
Classifier: License :: OSI Approved :: MIT License
Classifier: Operating System :: OS Independent
Requires-Python: >=3.6
Requires-Dist: pandas
Requires-Dist: numpy
Requires-Dist: scikit-learn
Requires-Dist: sweetviz
Requires-Dist: douroucoulisay
Requires-Dist: xgboost
